[
  {
    "id": 1,
    "title": "Tip #1: Hydrate Smartly",
    "summary": "A short, actionable idea to improve daily wellbeing.",
    "description": "Detailed guidance on how to apply this tip, suggested schedule, and ways to measure progress.",
    "category": "nutrition",
    "difficulty": "easy",
    "time": "15 mins",
    "image": "../images/bady-abbas-chrXKN7J8ic-unsplash.jpg"
  },
  {
    "id": 2,
    "title": "Tip #2: Walk More",
    "summary": "A short, actionable idea to improve daily wellbeing.",
    "description": "Detailed guidance on how to apply this tip, suggested schedule, and ways to measure progress.",
    "category": "fitness",
    "difficulty": "moderate",
    "time": "20 mins",
    "image": "../images/caju-gomes-QDq3YliZg48-unsplash.jpg"
  },
  {
    "id": 3,
    "title": "Tip #3: Stack Tiny Habits",
    "summary": "A short, actionable idea to improve daily wellbeing.",
    "description": "Detailed guidance on how to apply this tip, suggested schedule, and ways to measure progress.",
    "category": "habit",
    "difficulty": "challenging",
    "time": "25 mins",
    "image": "../images/christopher-campbell-kFCdfLbu6zA-unsplash.jpg"
  },
  {
    "id": 4,
    "title": "Tip #4: Hydrate Smartly",
    "summary": "A short, actionable idea to improve daily wellbeing.",
    "description": "Detailed guidance on how to apply this tip, suggested schedule, and ways to measure progress.",
    "category": "nutrition",
    "difficulty": "easy",
    "time": "10 mins",
    "image": "../images/gerson-repreza-JRpq0AvlF-g-unsplash.jpg"
  },
  {
    "id": 5,
    "title": "Tip #5: Walk More",
    "summary": "A short, actionable idea to improve daily wellbeing.",
    "description": "Detailed guidance on how to apply this tip, suggested schedule, and ways to measure progress.",
    "category": "fitness",
    "difficulty": "moderate",
    "time": "15 mins",
    "image": "../images/heather-ford-Ug7kk0kThLk-unsplash.jpg"
  },
  {
    "id": 6,
    "title": "Tip #6: Stack Tiny Habits",
    "summary": "A short, actionable idea to improve daily wellbeing.",
    "description": "Detailed guidance on how to apply this tip, suggested schedule, and ways to measure progress.",
    "category": "habit",
    "difficulty": "challenging",
    "time": "20 mins",
    "image": "../images/hyttalo-souza-a1p0Z7RSkL8-unsplash.jpg"
  },
  {
    "id": 7,
    "title": "Tip #7: Hydrate Smartly",
    "summary": "A short, actionable idea to improve daily wellbeing.",
    "description": "Detailed guidance on how to apply this tip, suggested schedule, and ways to measure progress.",
    "category": "nutrition",
    "difficulty": "easy",
    "time": "25 mins",
    "image": "../images/jason-briscoe-GrdJp16CPk8-unsplash.jpg"
  },
  {
    "id": 8,
    "title": "Tip #8: Walk More",
    "summary": "A short, actionable idea to improve daily wellbeing.",
    "description": "Detailed guidance on how to apply this tip, suggested schedule, and ways to measure progress.",
    "category": "fitness",
    "difficulty": "moderate",
    "time": "10 mins",
    "image": "../images/jc-gellidon-UIp163xCV6w-unsplash.jpg"
  },
  {
    "id": 9,
    "title": "Tip #9: Stack Tiny Habits",
    "summary": "A short, actionable idea to improve daily wellbeing.",
    "description": "Detailed guidance on how to apply this tip, suggested schedule, and ways to measure progress.",
    "category": "habit",
    "difficulty": "challenging",
    "time": "15 mins",
    "image": "../images/jenny-hill-Io2Zgb3_kdk-unsplash.jpg"
  },
  {
    "id": 10,
    "title": "Tip #10: Hydrate Smartly",
    "summary": "A short, actionable idea to improve daily wellbeing.",
    "description": "Detailed guidance on how to apply this tip, suggested schedule, and ways to measure progress.",
    "category": "nutrition",
    "difficulty": "easy",
    "time": "20 mins",
    "image": "../images/kaylee-garrett-GaprWyIw66o-unsplash.jpg"
  },
  {
    "id": 11,
    "title": "Tip #11: Walk More",
    "summary": "A short, actionable idea to improve daily wellbeing.",
    "description": "Detailed guidance on how to apply this tip, suggested schedule, and ways to measure progress.",
    "category": "fitness",
    "difficulty": "moderate",
    "time": "25 mins",
    "image": "../images/mariana-medvedeva-usfIE5Yc7PY-unsplash.jpg"
  },
  {
    "id": 12,
    "title": "Tip #12: Stack Tiny Habits",
    "summary": "A short, actionable idea to improve daily wellbeing.",
    "description": "Detailed guidance on how to apply this tip, suggested schedule, and ways to measure progress.",
    "category": "habit",
    "difficulty": "challenging",
    "time": "10 mins",
    "image": "../images/national-cancer-institute-L8tWZT4CcVQ-unsplash.jpg"
  },
  {
    "id": 13,
    "title": "Tip #13: Hydrate Smartly",
    "summary": "A short, actionable idea to improve daily wellbeing.",
    "description": "Detailed guidance on how to apply this tip, suggested schedule, and ways to measure progress.",
    "category": "nutrition",
    "difficulty": "easy",
    "time": "15 mins",
    "image": "../images/samantha-gades-k95uqdEe8R4-unsplash.jpg"
  },
  {
    "id": 14,
    "title": "Tip #14: Walk More",
    "summary": "A short, actionable idea to improve daily wellbeing.",
    "description": "Detailed guidance on how to apply this tip, suggested schedule, and ways to measure progress.",
    "category": "fitness",
    "difficulty": "moderate",
    "time": "20 mins",
    "image": "../images/thomas-yohei-BAlBUJb-SXQ-unsplash.jpg"
  },
  {
    "id": 15,
    "title": "Tip #15: Stack Tiny Habits",
    "summary": "A short, actionable idea to improve daily wellbeing.",
    "description": "Detailed guidance on how to apply this tip, suggested schedule, and ways to measure progress.",
    "category": "habit",
    "difficulty": "challenging",
    "time": "25 mins",
    "image": "../images/victoria-aleksandrova-9zsiNYwvYCM-unsplash.jpg"
  }
]